LICENSE
MANIFEST.in
README.rst
requirements.txt
setup.py
aliyunauth/__init__.py
aliyunauth/cms.py
aliyunauth/consts.py
aliyunauth/ecs.py
aliyunauth/oss.py
aliyunauth/rds.py
aliyunauth/sign_ver_1_0.py
aliyunauth/slb.py
aliyunauth/url.py
aliyunauth/utils.py
requests_aliyun.egg-info/PKG-INFO
requests_aliyun.egg-info/SOURCES.txt
requests_aliyun.egg-info/dependency_links.txt
requests_aliyun.egg-info/not-zip-safe
requests_aliyun.egg-info/requires.txt
requests_aliyun.egg-info/top_level.txt
tests/requirements.txt